other_package/__init__.py
other_package/abc.py
poetry102/__init__.py
poetry102/main.py
poetry102/xyz.py
poetry102-0.1.2.dist-info/METADATA
poetry102-0.1.2.dist-info/WHEEL
poetry102-0.1.2.dist-info/entry_points.txt
poetry102-0.1.2.dist-info/RECORD
